geizhalscrawler/__init__.py
geizhalscrawler/geizhalscrawler.py
geizhalscrawler-0.1.dist-info/LICENSE
geizhalscrawler-0.1.dist-info/METADATA
geizhalscrawler-0.1.dist-info/WHEEL
geizhalscrawler-0.1.dist-info/top_level.txt
geizhalscrawler-0.1.dist-info/RECORD
